mcp_server_dongjunqaq/__init__.py
mcp_server_dongjunqaq/tools.py
mcp_server_dongjunqaq-0.7.1.dist-info/WHEEL
mcp_server_dongjunqaq-0.7.1.dist-info/entry_points.txt
mcp_server_dongjunqaq-0.7.1.dist-info/METADATA
mcp_server_dongjunqaq-0.7.1.dist-info/RECORD
