Metadata-Version: 2.3
Name: mcp-server-dongjunqaq
Version: 0.7.1
Summary: DongJun的MCP Server
Author: DongJun
Author-email: DongJun <2360052818@qq.com>
Requires-Dist: mcp[cli]>=1.12.3
Requires-Dist: openai>=1.99.5
Requires-Dist: psutil>=7.0.0
Requires-Dist: yt-dlp>=2025.7.21
Requires-Python: >=3.11
